cloudkittydashboard/__init__.py
cloudkittydashboard/utils.py
cloudkittydashboard/api/__init__.py
cloudkittydashboard/api/cloudkitty.py
cloudkittydashboard/dashboards/__init__.py
cloudkittydashboard/dashboards/admin/__init__.py
cloudkittydashboard/dashboards/admin/hashmap/__init__.py
cloudkittydashboard/dashboards/admin/hashmap/forms.py
cloudkittydashboard/dashboards/admin/hashmap/panel.py
cloudkittydashboard/dashboards/admin/hashmap/tables.py
cloudkittydashboard/dashboards/admin/hashmap/tests.py
cloudkittydashboard/dashboards/admin/hashmap/urls.py
cloudkittydashboard/dashboards/admin/hashmap/views.py
cloudkittydashboard/dashboards/admin/hashmap/templates/hashmap/_field_create.html
cloudkittydashboard/dashboards/admin/hashmap/templates/hashmap/_group_create.html
cloudkittydashboard/dashboards/admin/hashmap/templates/hashmap/_mapping_create.html
cloudkittydashboard/dashboards/admin/hashmap/templates/hashmap/_service_create.html
cloudkittydashboard/dashboards/admin/hashmap/templates/hashmap/_threshold_create.html
cloudkittydashboard/dashboards/admin/hashmap/templates/hashmap/field_create.html
cloudkittydashboard/dashboards/admin/hashmap/templates/hashmap/field_details.html
cloudkittydashboard/dashboards/admin/hashmap/templates/hashmap/group_create.html
cloudkittydashboard/dashboards/admin/hashmap/templates/hashmap/group_details.html
cloudkittydashboard/dashboards/admin/hashmap/templates/hashmap/mapping_create.html
cloudkittydashboard/dashboards/admin/hashmap/templates/hashmap/service_create.html
cloudkittydashboard/dashboards/admin/hashmap/templates/hashmap/service_details.html
cloudkittydashboard/dashboards/admin/hashmap/templates/hashmap/services_list.html
cloudkittydashboard/dashboards/admin/hashmap/templates/hashmap/threshold_create.html
cloudkittydashboard/dashboards/admin/modules/__init__.py
cloudkittydashboard/dashboards/admin/modules/forms.py
cloudkittydashboard/dashboards/admin/modules/panel.py
cloudkittydashboard/dashboards/admin/modules/tables.py
cloudkitty_dashboard-21.0.0.dist-info/AUTHORS
cloudkitty_dashboard-21.0.0.dist-info/LICENSE
cloudkitty_dashboard-21.0.0.dist-info/METADATA
cloudkitty_dashboard-21.0.0.dist-info/WHEEL
cloudkitty_dashboard-21.0.0.dist-info/pbr.json
cloudkitty_dashboard-21.0.0.dist-info/top_level.txt
cloudkitty_dashboard-21.0.0.dist-info/RECORD
