Metadata-Version: 2.1
Name: cloudkitty-dashboard
Version: 21.0.0
Summary: CloudKitty Horizon dashboard
Home-page: https://docs.openstack.org/cloudkitty-dashboard/latest/
Author: OpenStack
Author-email: openstack-discuss@lists.openstack.org
Classifier: Environment :: OpenStack
Classifier: Intended Audience :: Information Technology
Classifier: Intended Audience :: System Administrators
Classifier: License :: OSI Approved :: Apache Software License
Classifier: Operating System :: POSIX :: Linux
Classifier: Programming Language :: Python
Classifier: Programming Language :: Python :: 3
Classifier: Programming Language :: Python :: Implementation :: CPython
Classifier: Programming Language :: Python :: 3 :: Only
Classifier: Programming Language :: Python :: 3.10
Classifier: Programming Language :: Python :: 3.11
Classifier: Programming Language :: Python :: 3.12
Classifier: Programming Language :: Python :: 3.13
Requires-Python: >=3.10
License-File: LICENSE
License-File: AUTHORS
Requires-Dist: pbr !=2.1.0,>=2.0.0
Requires-Dist: python-cloudkittyclient >=0.5.0
Requires-Dist: horizon >=17.1.0
Requires-Dist: XStatic-D3 >=3.5.17.0
Requires-Dist: XStatic-Rickshaw >=1.5
